setup.py
simpleauth/__init__.py
simpleauth/handler.py
simpleauth.egg-info/PKG-INFO
simpleauth.egg-info/SOURCES.txt
simpleauth.egg-info/dependency_links.txt
simpleauth.egg-info/requires.txt
simpleauth.egg-info/top_level.txt