Metadata-Version: 1.1
Name: simpleauth
Version: 0.1.5
Summary: A simple auth handler for Google App Engine supporting OAuth 1.0a, 2.0 and OpenID
Home-page: https://github.com/crhym3/simpleauth
Author: Alex Vaghin (alex@cloudware.it)
Author-email: UNKNOWN
License: MIT
Download-URL: https://github.com/crhym3/simpleauth/archive/master.zip
Keywords: oauth oauth2 openid appengine google
Platform: any
Classifier: Development Status :: 4 - Beta
Classifier: Environment :: Web Environment
Classifier: Intended Audience :: Developers
Classifier: License :: OSI Approved :: MIT License
Classifier: Programming Language :: Python
Classifier: Programming Language :: Python :: 2.7
Classifier: Topic :: Internet :: WWW/HTTP
Classifier: Topic :: Security
Classifier: Topic :: Software Development :: Libraries
